{
  "project_info": {
    "project_number": "668809459861",
    "firebase_url": "https://soleeklabtask-539aa.firebaseio.com",
    "project_id": "soleeklabtask-539aa",
    "storage_bucket": "soleeklabtask-539aa.appspot.com"
  },
  "client": [
    {
      "client_info": {
        "mobilesdk_app_id": "1:668809459861:android:b42ab0be97a01fbf",
        "android_client_info": {
          "package_name": "com.example.em7mdmoussa.soleeklabtask"
        }
      },
      "oauth_client": [
        {
          "client_id": "668809459861-dnth61m6dlkf9dih7od4oqe86ramj2hg.apps.googleusercontent.com",
          "client_type": 3
        }
      ],
      "api_key": [
        {
          "current_key": "AIzaSyC22si9R1SgEMBHNWeCSN4Sg8CFGm-NSrE"
        }
      ],
      "services": {
        "analytics_service": {
          "status": 1
        },
        "appinvite_service": {
          "status": 1,
          "other_platform_oauth_client": []
        },
        "ads_service": {
          "status": 2
        }
      }
    }
  ],
  "configuration_version": "1"
}